pykumaapi2/__init__.py
pykumaapi2/client.py
pykumaapi2/rest_client.py
pykumaapi2/socket_client.py
pykumaapi2-0.1.2.dist-info/licenses/LICENSE
pykumaapi2-0.1.2.dist-info/METADATA
pykumaapi2-0.1.2.dist-info/WHEEL
pykumaapi2-0.1.2.dist-info/top_level.txt
pykumaapi2-0.1.2.dist-info/RECORD
