Metadata-Version: 2.4
Name: pykumaapi2
Version: 0.1.2
Summary: Python client for Uptime Kuma REST and Socket.io APIs
Home-page: https://github.com/emadomedher/pyKumaAPI
Author: Emad O. Medher
Author-email: lsumedher@gmail.com
Project-URL: Bug Reports, https://github.com/emadomedher/pyKumaAPI/issues
Project-URL: Source, https://github.com/emadomedher/pyKumaAPI
Project-URL: Documentation, https://github.com/emadomedher/pyKumaAPI#readme
Keywords: uptime-kuma monitoring api client socket.io rest pykumaapi2
Classifier: Development Status :: 4 - Beta
Classifier: Intended Audience :: Developers
Classifier: License :: OSI Approved :: MIT License
Classifier: Operating System :: OS Independent
Classifier: Programming Language :: Python :: 3
Classifier: Programming Language :: Python :: 3.8
Classifier: Programming Language :: Python :: 3.9
Classifier: Programming Language :: Python :: 3.10
Classifier: Programming Language :: Python :: 3.11
Classifier: Topic :: Software Development :: Libraries :: Python Modules
Classifier: Topic :: System :: Monitoring
Requires-Python: >=3.8
License-File: LICENSE
Requires-Dist: python-socketio>=5.0.0
Requires-Dist: aiohttp>=3.8.0
Requires-Dist: requests>=2.25.0
Provides-Extra: dev
Requires-Dist: pytest>=6.0; extra == "dev"
Requires-Dist: pytest-asyncio>=0.21.0; extra == "dev"
Requires-Dist: black>=22.0.0; extra == "dev"
Requires-Dist: flake8>=4.0.0; extra == "dev"
Requires-Dist: mypy>=0.950; extra == "dev"
Dynamic: author
Dynamic: author-email
Dynamic: classifier
Dynamic: description
Dynamic: description-content-type
Dynamic: home-page
Dynamic: keywords
Dynamic: license-file
Dynamic: project-url
Dynamic: provides-extra
Dynamic: requires-dist
Dynamic: requires-python
Dynamic: summary
